lolaml/__init__.py
lolaml/__main__.py
lolaml/cli.py
lolaml/config.py
lolaml/core.py
lolaml/data.py
lolaml/incubator.py
lolaml/remotes.py
lolaml/storage.py
lolaml/templates/index.html
lolaml/tests/__init__.py
lolaml/tests/conftest.py
lolaml/utils.py
lolaml-0.0.4.dist-info/entry_points.txt
lolaml-0.0.4.dist-info/LICENSE
lolaml-0.0.4.dist-info/WHEEL
lolaml-0.0.4.dist-info/METADATA
lolaml-0.0.4.dist-info/RECORD
