Metadata-Version: 2.1
Name: lolaml
Version: 0.0.4
Summary: LolaML - track your ML experiments
Home-page: https://pypi.org/project/lolaml
License: UNKNOWN
Author: Stefan Otte
Author-email: stefan.otte@gmail.com
Requires-Python: >=3.6,<4.0
Classifier: Development Status :: 4 - Beta
Classifier: Natural Language :: English
Classifier: Operating System :: OS Independent
Classifier: Programming Language :: Python
Classifier: Programming Language :: Python :: 3
Classifier: Programming Language :: Python :: 3.6
Classifier: Programming Language :: Python :: 3.7
Classifier: Topic :: Scientific/Engineering :: Artificial Intelligence
Requires-Dist: click (>=6.0,<7.0)
Requires-Dist: cloudstorage (>=0.9.0,<0.10.0)
Requires-Dist: dataclasses (>=0.6.0,<0.7.0)
Requires-Dist: filelock (>=3.0,<4.0)
Requires-Dist: google-cloud-storage (>=1.14,<2.0)
Requires-Dist: itsdangerous (>=1.1,<2.0)
Requires-Dist: minilog (>=0.4,<0.5)
Requires-Dist: tomlkit (>=0.5.3,<0.6.0)
Requires-Dist: xattr (>=0.9.6,<0.10.0)
Project-URL: Documentation, https://lolaml.readthedocs.io
Project-URL: Repository, https://gitlab.com/stefan-otte/lolaml/
